{"cameraMode":{"drawMode":0,"name":"Shaded","section":"Shading Mode"},"sceneLighting":true,"audioPlay":false,"sceneViewState":{"showFog":true,"showMaterialUpdate":false,"showSkybox":true,"showFlares":true,"showImageEffects":true,"showParticleSystems":true},"in2DMode":false,"pivot":{"x":111.38175964355469,"y":7.620368957519531,"z":7.192365646362305},"rotation":{"x":-0.23156319558620454,"y":0.5086806416511536,"z":-0.14423757791519166,"w":-0.8166107535362244},"size":158.0255126953125,"orthographic":false}